LICENSE
README.md
setup.py
thfund_monitor/__init__.py
thfund_monitor/monitor_utils.py
thfund_monitor.egg-info/PKG-INFO
thfund_monitor.egg-info/SOURCES.txt
thfund_monitor.egg-info/dependency_links.txt
thfund_monitor.egg-info/requires.txt
thfund_monitor.egg-info/top_level.txt