Metadata-Version: 2.1
Name: thfund-monitor
Version: 0.0.2
Summary: 监控埋点封装
Home-page: https://github.com/pypa/sampleproject
Author: LiuYong
Author-email: liuyong@thfund.com.cn
License: MIT License
Keywords: monitor
Classifier: License :: OSI Approved :: MIT License
Classifier: Operating System :: OS Independent
Classifier: Programming Language :: Python :: 3
License-File: LICENSE
Requires-Dist: flask
Requires-Dist: prometheus_client
Requires-Dist: os
Requires-Dist: time
Requires-Dist: functools
